hdmimatrix/__init__.py
hdmimatrix/hdmimatrix.py
hdmimatrix-0.0.6.dist-info/licenses/LICENSE
hdmimatrix-0.0.6.dist-info/METADATA
hdmimatrix-0.0.6.dist-info/WHEEL
hdmimatrix-0.0.6.dist-info/top_level.txt
hdmimatrix-0.0.6.dist-info/RECORD
