Metadata-Version: 2.4
Name: hdmimatrix
Version: 0.0.6
Summary: Python HDMI Matrix control library for AVGear and possibly other HDMI matrix controllers
Author-email: Mark Lynch <marklynch@gmail.com>
License-Expression: MIT
Project-URL: Homepage, https://github.com/marklynch/hdmimatrix
Project-URL: Issues, https://github.com/marklynch/hdmimatrix/issues
Classifier: Programming Language :: Python :: 3
Classifier: Operating System :: OS Independent
Requires-Python: >=3.9
License-File: LICENSE
Dynamic: license-file
